{
    "image": "mcr.microsoft.com/azure-powershell:ubuntu-22.04",
    "customizations": {
        "vscode": {
            "extensions": [
                "ms-vscode.powershell",
                "ms-azuretools.vscode-bicep",
                "github.vscode-github-actions",
                "github.copilot",
                "davidanson.vscode-markdownlint"
            ]
        }
    },
    "features": {
        "ghcr.io/devcontainers/features/git:1": {}
    },
    "postCreateCommand": "pwsh -File '/workspaces/GhCloudOps/.devcontainer/setup.ps1'"
}
